README.md
setup.py
cloud_ml_sdk/__init__.py
cloud_ml_sdk/client.py
cloud_ml_sdk.egg-info/PKG-INFO
cloud_ml_sdk.egg-info/SOURCES.txt
cloud_ml_sdk.egg-info/dependency_links.txt
cloud_ml_sdk.egg-info/entry_points.txt
cloud_ml_sdk.egg-info/requires.txt
cloud_ml_sdk.egg-info/top_level.txt
cloud_ml_sdk/command/__init__.py
cloud_ml_sdk/command/color_util.py
cloud_ml_sdk/command/command.py
cloud_ml_sdk/command/command_admin.py
cloud_ml_sdk/command/constant.py
cloud_ml_sdk/command/util.py
cloud_ml_sdk/models/__init__.py
cloud_ml_sdk/models/ceph_service.py
cloud_ml_sdk/models/constant.py
cloud_ml_sdk/models/dev_env.py
cloud_ml_sdk/models/dev_server.py
cloud_ml_sdk/models/model_service.py
cloud_ml_sdk/models/models_util.py
cloud_ml_sdk/models/namespace_quota_service.py
cloud_ml_sdk/models/namespace_service.py
cloud_ml_sdk/models/namespace_user_service.py
cloud_ml_sdk/models/pipeline.py
cloud_ml_sdk/models/quota.py
cloud_ml_sdk/models/schedule.py
cloud_ml_sdk/models/secret_service.py
cloud_ml_sdk/models/tensorboard_service.py
cloud_ml_sdk/models/train_job.py
cloud_ml_sdk/predict_client/__init__.py
cloud_ml_sdk/predict_client/generic_predict_client.py
cloud_ml_sdk/predict_client/model_pb2.py
cloud_ml_sdk/predict_client/predict_pb2.py
cloud_ml_sdk/predict_client/prediction_service_pb2.py