Metadata-Version: 1.0
Name: cloud-ml-sdk
Version: 0.3.71
Summary: Xiaomi Cloud-ml SDK
Home-page: UNKNOWN
Author: Xiaomi
Author-email: UNKNOWN
License: UNKNOWN
Platform: UNKNOWN
